hebrew_python/LICENSE
hebrew_python/__init__.py
hebrew_python/__main__.py
hebrew_python/error_hook.py
hebrew_python/hebrew_data.py
hebrew_python/hook.py
hebrew_python/ipython.py
hebrew_python/אקראי.py
hebrew_python/ממשק.py
hebrew_python/שגיאות.py
hebrew_python-0.1.7.dist-info/entry_points.txt
hebrew_python-0.1.7.dist-info/WHEEL
hebrew_python-0.1.7.dist-info/METADATA
hebrew_python-0.1.7.dist-info/RECORD
