Metadata-Version: 2.1
Name: hebrew-python
Version: 0.1.7
Summary: write python in Hebrew
Home-page: https://github.com/matan-h/hebrew-python
License: BSD-4-Clause
Author: matan h
Author-email: matan.honig2@gmail.com
Requires-Python: >=3.6,<4.0
Classifier: License :: Other/Proprietary License
Classifier: Programming Language :: Python :: 3
Classifier: Programming Language :: Python :: 3.10
Classifier: Programming Language :: Python :: 3.6
Classifier: Programming Language :: Python :: 3.7
Classifier: Programming Language :: Python :: 3.8
Classifier: Programming Language :: Python :: 3.9
Provides-Extra: errors
Requires-Dist: friendly-traceback (>=0.4.36,<0.5.0); extra == "errors"
Requires-Dist: ideas (>=0.0.22,<0.0.23)
Project-URL: issues, https://github.com/matan-h/hebrew-python/issues
